[
  {
    "name": "1 MONTH",
    "price": "150",
    "offer_price": "90",
    "duration": "",
    "link": "/one-month-program.html",
    "pic": "./assets/img/package-1.png",
    "details": [
      "Initial Discovery Call",
      "Customized Diet Plans",
      "Supplementation Advice",
      "Workout Schedules",
      "Weekly Progress Check-ins",
      "Support When You Need It"
    ]
  },
  {
    "name": "3 MONTHS",
    "price": "300",
    "offer_price": "220",
    "duration": "",
    "link": "/three-months-program.html",
    "pic": "./assets/img/package-3.png",
    "details": [
      "Initial Discovery Call",
      "Customized Diet Plans",
      "Supplementation Advice",
      "Workout Schedules",
      "Weekly Progress Check-ins",
      "Support When You Need It"
    ]
  },
  {
    "name": "6 MONTHS",
    "price": "550",
    "offer_price": "460",
    "duration": "",
    "link": "/six-months-program.html",
    "pic": "./assets/img/package-2.png",
    "details": [
      "Initial Discovery Call",
      "Customized Diet Plans",
      "Supplementation Advice",
      "Workout Schedules",
      "Weekly Progress Check-ins",
      "Support When You Need It"
    ]
  },
  {
    "name": "ONLY DIET SCHEDULE",
    "price": "60",
    "offer_price": "35",
    "duration": "M",
    "link": "/only-diet-schedule.html",
    "pic": "./assets/img/package-4.png",
    "details": [
      "Customized Diet Schedule",
      "Non-Veg, Veg and Vegan options available",
      "Supplementation Advice included"
    ]
  }
]
